grafeo/__init__.py
grafeo/cli.py
grafeo/grafeo.cpython-314-x86_64-linux-gnu.so
grafeo/py.typed
grafeo-0.2.0.dist-info/METADATA
grafeo-0.2.0.dist-info/WHEEL
grafeo-0.2.0.dist-info/entry_points.txt
grafeo-0.2.0.dist-info/RECORD
