Metadata-Version: 2.4
Name: grafeo
Version: 0.2.0
Classifier: Development Status :: 3 - Alpha
Classifier: Intended Audience :: Developers
Classifier: Intended Audience :: Science/Research
Classifier: License :: OSI Approved :: Apache Software License
Classifier: Operating System :: OS Independent
Classifier: Programming Language :: Python :: 3
Classifier: Programming Language :: Python :: 3.12
Classifier: Programming Language :: Python :: 3.13
Classifier: Programming Language :: Python :: 3.14
Classifier: Programming Language :: Rust
Classifier: Topic :: Database
Classifier: Topic :: Database :: Database Engines/Servers
Classifier: Topic :: Scientific/Engineering :: Artificial Intelligence
Classifier: Typing :: Typed
Requires-Dist: solvor>=0.5.5
Requires-Dist: click>=8.3.1 ; extra == 'cli'
Requires-Dist: pytest>=9.0.2 ; extra == 'dev'
Requires-Dist: pytest-asyncio>=1.3.0 ; extra == 'dev'
Requires-Dist: ty>=0.0.14 ; extra == 'dev'
Requires-Dist: ruff>=0.14.14 ; extra == 'dev'
Provides-Extra: cli
Provides-Extra: dev
Summary: A high-performance, embeddable graph database with Python bindings
Keywords: graph,database,gql,knowledge-graph,embedded
Author: S.T. Grond
License: Apache-2.0
Requires-Python: >=3.12
Project-URL: Documentation, https://grafeo.dev/user-guide/
Project-URL: Homepage, https://grafeo.dev
Project-URL: Issues, https://github.com/GrafeoDB/grafeo/issues
Project-URL: Repository, https://github.com/GrafeoDB/grafeo
